Workbook

Sheet Read me
A1: CHURCH TIMES NIGERIA · PROPOSED OPERATING SYSTEM
A4: Status | B4: Planning template, not actual accounts or a forecast. Blue cells are editable. Formula cells are not protected; do not overwrite them unintentionally.
A5: Model | B5: Monthly revenue, contribution and break-even membership. Defaults are unvalidated hypotheses. Revenue is not collected cash. Excludes taxes, payment fees and bad debt until separately added.
A6: Cash 13 weeks | B6: Enter actual receipts and payments by due week. Defaults show zero receipts and an estimated weekly fixed-cost allocation. Replace the smoothed cost estimate with actual payment dates and amounts. Negative cash flags required funding; positive cash does not prove profitability.
A7: Pipeline | B7: Enter permissioned prospects only. Suggested stage probabilities are not forecasts. Weighted proposals are neither earned revenue nor cash. No real contacts are included.
A8: Special edition | B8: Verify the founder’s provisional ₦2m against a fresh quote. Adjust contingency, tax and commissions as necessary. Commit production only when cleared cash covers all approved committed costs, and signed terms/rights/capacity are confirmed.
A9: Dashboard | B9: Actual monthly values are blank/zero placeholders. Populate from reconciled bank/accounting and member records. Cash runway is simplified; use the dated 13-week forecast for decisions.
A10: Privacy | B10: Keep the completed workbook in an access-controlled company location. Do not put credentials or payment-card details here. Consent source and opt-out records must be respected.
A11: Governance | B11: Founder/editor guards mission; commercial lead owns sales and collections; digital owner operates distribution; bookkeeper reconciles. Have a second person review material spending and conflicts.
A12: Next step | B12: Approve owners, actual starting cash, costs, legal name, tax treatment, contact-list permissions, and current website/CMS manager. See docs/financial-plan.md and docs/research-and-discovery.md.

Sheet Model
A1: MONTHLY SCENARIO · HYPOTHESES, NOT ACTUAL ACCOUNTS
A4: Paying members | B4: 200 | D4: Gross revenue | E4: =B4*B5+B6*B7+B8 -> 1200000
A5: Membership fee | B5: 2500 | D5: Delivery costs | E5: =B4*B5*B10+B6*B7*B11+B8*B12 -> 265000
A6: Paying sponsors | B6: 2 | D6: Contribution | E6: =E4-E5 -> 935000
A7: Fee per sponsor | B7: 200000 | D7: Operating result | E7: =E6-B9 -> 85000
A8: Project revenue | B8: 300000 | D8: Operating margin | E8: =IF(E4=0,0,E7/E4) -> 0.070833333
A9: Fixed costs | B9: 850000 | D9: Break-even members | E9: =IF(MAX(0,B9-B6*B7*(1-B11)-B8*(1-B12))=0,0,IF(B5*(1-B10)>0,ROUNDUP(MAX(0,B9-B6*B7*(1-B11)-B8*(1-B12))/(B5*(1-B10)),0),"Not attainable")) -> 163
A10: Member delivery rate | B10: 0.1 | D10: 3-month fixed-cost reserve | E10: =B9*3 -> 2550000
A11: Sponsor delivery rate | B11: 0.2
A12: Project delivery rate | B12: 0.45
A15: Baseline: ₦85,000 operating surplus before excluded costs; 163 members to break even if sponsors/projects repeat. This is fragile. The contact list, actual cash and willingness to pay are unknown. Revenue does not equal receipts.

Sheet Cash 13 weeks
A1: CASH FORECAST · INPUT COLLECTED RECEIPTS AND DATED PAYMENTS
A2: Opening cash | B2: 0 | C2: Zero placeholder. Enter unrestricted bank cash; keep client delivery/tax funds separate.
A3: Week | B3: Opening cash | C3: Collected receipts | D3: Fixed payments | E3: Project / other payments | F3: Closing cash | G3: Funding needed | H3: Receipt / expense notes | I3: Owner
A4: 1 | B4: =$B$2 -> 0 | C4: 0 | D4: =Model!$B$9*12/52 -> 196153.85 | E4: 0 | F4: =B4+C4-D4-E4 -> -196153.85 | G4: =MAX(0,-F4) -> 196153.85
A5: 2 | B5: =F4 -> -196153.85 | C5: 0 | D5: =Model!$B$9*12/52 -> 196153.85 | E5: 0 | F5: =B5+C5-D5-E5 -> -392307.69 | G5: =MAX(0,-F5) -> 392307.69
A6: 3 | B6: =F5 -> -392307.69 | C6: 0 | D6: =Model!$B$9*12/52 -> 196153.85 | E6: 0 | F6: =B6+C6-D6-E6 -> -588461.54 | G6: =MAX(0,-F6) -> 588461.54
A7: 4 | B7: =F6 -> -588461.54 | C7: 0 | D7: =Model!$B$9*12/52 -> 196153.85 | E7: 0 | F7: =B7+C7-D7-E7 -> -784615.38 | G7: =MAX(0,-F7) -> 784615.38
A8: 5 | B8: =F7 -> -784615.38 | C8: 0 | D8: =Model!$B$9*12/52 -> 196153.85 | E8: 0 | F8: =B8+C8-D8-E8 -> -980769.23 | G8: =MAX(0,-F8) -> 980769.23
A9: 6 | B9: =F8 -> -980769.23 | C9: 0 | D9: =Model!$B$9*12/52 -> 196153.85 | E9: 0 | F9: =B9+C9-D9-E9 -> -1176923.1 | G9: =MAX(0,-F9) -> 1176923.1
A10: 7 | B10: =F9 -> -1176923.1 | C10: 0 | D10: =Model!$B$9*12/52 -> 196153.85 | E10: 0 | F10: =B10+C10-D10-E10 -> -1373076.9 | G10: =MAX(0,-F10) -> 1373076.9
A11: 8 | B11: =F10 -> -1373076.9 | C11: 0 | D11: =Model!$B$9*12/52 -> 196153.85 | E11: 0 | F11: =B11+C11-D11-E11 -> -1569230.8 | G11: =MAX(0,-F11) -> 1569230.8
A12: 9 | B12: =F11 -> -1569230.8 | C12: 0 | D12: =Model!$B$9*12/52 -> 196153.85 | E12: 0 | F12: =B12+C12-D12-E12 -> -1765384.6 | G12: =MAX(0,-F12) -> 1765384.6
A13: 10 | B13: =F12 -> -1765384.6 | C13: 0 | D13: =Model!$B$9*12/52 -> 196153.85 | E13: 0 | F13: =B13+C13-D13-E13 -> -1961538.5 | G13: =MAX(0,-F13) -> 1961538.5
A14: 11 | B14: =F13 -> -1961538.5 | C14: 0 | D14: =Model!$B$9*12/52 -> 196153.85 | E14: 0 | F14: =B14+C14-D14-E14 -> -2157692.3 | G14: =MAX(0,-F14) -> 2157692.3
A15: 12 | B15: =F14 -> -2157692.3 | C15: 0 | D15: =Model!$B$9*12/52 -> 196153.85 | E15: 0 | F15: =B15+C15-D15-E15 -> -2353846.2 | G15: =MAX(0,-F15) -> 2353846.2
A16: 13 | B16: =F15 -> -2353846.2 | C16: 0 | D16: =Model!$B$9*12/52 -> 196153.85 | E16: 0 | F16: =B16+C16-D16-E16 -> -2550000 | G16: =MAX(0,-F16) -> 2550000
A19: Fixed payments are initially spread evenly from the Model sheet for illustration. Replace blue cells with actual due-date amounts; enter project/tax/fees/refunds separately. Zero receipts and zero starting cash intentionally show a funding shortfall, not a prediction. Do not substitute invoices for collected cash.

Sheet Pipeline
A1: PERMISSIONED SALES PIPELINE · NO REAL CONTACTS INCLUDED
A3: Organisation | B3: Contact / permission | C3: Offer | D3: Stage | E3: Proposed amount | F3: Probability | G3: Weighted proposal | H3: Cash collected | I3: Delivery cost estimate | J3: Next action date | K3: Next action | L3: Owner | M3: Renewal / restrictions
E4: 0 | F4: 0 | G4: =E4*F4 -> 0 | H4: 0 | I4: 0
E5: 0 | F5: 0 | G5: =E5*F5 -> 0 | H5: 0 | I5: 0
E6: 0 | F6: 0 | G6: =E6*F6 -> 0 | H6: 0 | I6: 0
E7: 0 | F7: 0 | G7: =E7*F7 -> 0 | H7: 0 | I7: 0
E8: 0 | F8: 0 | G8: =E8*F8 -> 0 | H8: 0 | I8: 0
E9: 0 | F9: 0 | G9: =E9*F9 -> 0 | H9: 0 | I9: 0
E10: 0 | F10: 0 | G10: =E10*F10 -> 0 | H10: 0 | I10: 0
E11: 0 | F11: 0 | G11: =E11*F11 -> 0 | H11: 0 | I11: 0
E12: 0 | F12: 0 | G12: =E12*F12 -> 0 | H12: 0 | I12: 0
E13: 0 | F13: 0 | G13: =E13*F13 -> 0 | H13: 0 | I13: 0
E14: 0 | F14: 0 | G14: =E14*F14 -> 0 | H14: 0 | I14: 0
E15: 0 | F15: 0 | G15: =E15*F15 -> 0 | H15: 0 | I15: 0
... E23: 0 | F23: 0 | G23: =E23*F23 -> 0 | H23: 0 | I23: 0
D25: Totals (not earned revenue) | E25: =SUM(E4:E23) -> 0 | G25: =SUM(G4:G23) -> 0 | H25: =SUM(H4:H23) -> 0 | I25: =SUM(I4:I23) -> 0
A28: Probabilities are planning estimates only. Signed proposals and weighted pipeline are not cash. Record permission/source, written terms, a named next action and collections. Sponsor influence over independent reporting is prohibited. No personal data should be imported without a lawful purpose and appropriate controls.

Sheet Special edition
A1: PRINT PROJECT · CASH GATE BEFORE PRODUCTION
A4: Verified all-in cost (provisional) | B4: 2000000
A5: Contingency rate | B5: 0.15
A6: Target margin on sales | B6: 0.2
A7: Cleared project cash | B7: 0
A10: Committed cost + contingency | B10: =B4*(1+B5) -> 2300000
A11: Sales required for target margin | B11: =B10/(1-B6) -> 2875000
A12: Cash coverage gap | B12: =MAX(0,B10-B7) -> 2300000
A13: Funding gate | B13: =IF(B7>=B10,"Cash covered; check other gates","HOLD: cash not covered") -> HOLD: cash not covered
A16: Gate is cash coverage plus signed terms, rights, capacity and independent editorial approval. ₦2m comes from the interview and is not a fresh quotation. Include tax, sales commission and delivery costs in the verified cost; if they depend on sales, revise the model before use. Do not spend deposits on unrelated operating losses.

Sheet Dashboard
A1: MONTHLY ACTUALS · ENTER RECONCILED RECORDS
A4: Unrestricted operating cash | B4: 0 | D4: Actual records are currently unknown. All zeros are placeholders, not verified results. Investigate any member reconciliation difference. Proposed concentration review trigger: 25%. Cash runway is meaningful only with realistic cash burn and exclusions for restricted funds.
A5: Monthly net cash burn | B5: 0
A6: Active paid members | B6: 0
A7: Members at start of month | B7: 0
A8: New paid members | B8: 0
A9: Cancelled / failed renewals | B9: 0
A10: Collected monthly receipts | B10: 0
A11: Largest sponsor receipts | B11: 0
A12: Overdue receivables | B12: 0
A15: Cash runway (months) | B15: =IF(B5>0,B4/B5,"Enter actual burn / not applicable") -> Enter actual burn / not applicable
A16: Monthly churn | B16: =IF(B7>0,B9/B7,0) -> 0
A17: Largest sponsor concentration | B17: =IF(B10>0,B11/B10,0) -> 0
A18: Expected closing member count | B18: =B7+B8-B9 -> 0
A19: Member reconciliation difference | B19: =B6-B18 -> 0
